[
  {
    "Type": "CharaPartsColorList",
    "Name": "CL_CH_F000_bdl_vst_001_01",
    "Class": "UScriptClass'CharaPartsColorList'",
    "Properties": {
      "ColorList": [
        {
          "IsValid": true,
          "Name": "",
          "BaseColor1": {
            "R": 1.0,
            "G": 1.0,
            "B": 1.0,
            "A": 1.0,
            "Hex": "FFFFFFFF"
          },
          "BaseColor2": {
            "R": 1.0,
            "G": 1.0,
            "B": 1.0,
            "A": 1.0,
            "Hex": "FFFFFFFF"
          },
          "BaseColor3": {
            "R": 1.0,
            "G": 1.0,
            "B": 1.0,
            "A": 1.0,
            "Hex": "FFFFFFFF"
          },
          "BaseColor4": {
            "R": 1.0,
            "G": 1.0,
            "B": 1.0,
            "A": 1.0,
            "Hex": "FFFFFFFF"
          }
        },
        {
          "IsValid": true,
          "Name": "",
          "BaseColor1": {
            "R": 0.375,
            "G": 0.05625,
            "B": 0.064746,
            "A": 1.0,
            "Hex": "FFA54348"
          },
          "BaseColor2": {
            "R": 1.0,
            "G": 1.0,
            "B": 1.0,
            "A": 1.0,
            "Hex": "FFFFFFFF"
          },
          "BaseColor3": {
            "R": 1.0,
            "G": 1.0,
            "B": 1.0,
            "A": 1.0,
            "Hex": "FFFFFFFF"
          },
          "BaseColor4": {
            "R": 1.0,
            "G": 1.0,
            "B": 1.0,
            "A": 1.0,
            "Hex": "FFFFFFFF"
          }
        },
        {
          "IsValid": true,
          "Name": "",
          "BaseColor1": {
            "R": 0.07,
            "G": 0.130712,
            "B": 0.2,
            "A": 1.0,
            "Hex": "FF4B657C"
          },
          "BaseColor2": {
            "R": 1.0,
            "G": 1.0,
            "B": 1.0,
            "A": 1.0,
            "Hex": "FFFFFFFF"
          },
          "BaseColor3": {
            "R": 1.0,
            "G": 1.0,
            "B": 1.0,
            "A": 1.0,
            "Hex": "FFFFFFFF"
          },
          "BaseColor4": {
            "R": 1.0,
            "G": 1.0,
            "B": 1.0,
            "A": 1.0,
            "Hex": "FFFFFFFF"
          }
        },
        {
          "IsValid": true,
          "Name": "",
          "BaseColor1": {
            "R": 0.198673,
            "G": 0.223228,
            "B": 0.15626,
            "A": 1.0,
            "Hex": "FF7B826E"
          },
          "BaseColor2": {
            "R": 1.0,
            "G": 1.0,
            "B": 1.0,
            "A": 1.0,
            "Hex": "FFFFFFFF"
          },
          "BaseColor3": {
            "R": 1.0,
            "G": 1.0,
            "B": 1.0,
            "A": 1.0,
            "Hex": "FFFFFFFF"
          },
          "BaseColor4": {
            "R": 1.0,
            "G": 1.0,
            "B": 1.0,
            "A": 1.0,
            "Hex": "FFFFFFFF"
          }
        }
      ]
    }
  }
]