[
  {
    "Type": "Function",
    "Name": "ExecuteUbergraph_PlayerGaugeBagCapacity",
    "Outer": "PlayerGaugeBagCapacity_C",
    "Class": "UScriptClass'Function'",
    "ChildProperties": [
      {
        "Type": "IntProperty",
        "Name": "EntryPoint",
        "Flags": "RF_Public",
        "ElementSize": 4,
        "PropertyFlags": "BlueprintVisible | BlueprintReadOnly | Parm"
      },
      {
        "Type": "DelegateProperty",
        "Name": "K2Node_CreateDelegate_OutputDelegate",
        "Flags": "RF_Public",
        "ElementSize": 20,
        "SignatureFunction": {
          "ObjectName": "DelegateFunction'SBOwnItemList:OwnItemPostUpdateItemsDelegate__DelegateSignature'",
          "ObjectPath": "/Script/SkyBlue"
        }
      },
      {
        "Type": "DelegateProperty",
        "Name": "K2Node_CreateDelegate_OutputDelegate_1",
        "Flags": "RF_Public",
        "ElementSize": 20,
        "SignatureFunction": {
          "ObjectName": "DelegateFunction'SBPlayerLiquidMemoryComponent:OnUseLiquidMemoryDelegate__DelegateSignature'",
          "ObjectPath": "/Script/SkyBlue"
        }
      },
      {
        "Type": "BoolProperty",
        "Name": "CallFunc_GetNetworkDataCache_IsValid",
        "Flags": "RF_Public",
        "ElementSize": 1,
        "FieldSize": 1,
        "ByteOffset": 0,
        "ByteMask": 1,
        "FieldMask": 255,
        "BoolSize": 1,
        "bIsNativeBool": true
      },
      {
        "Type": "ObjectProperty",
        "Name": "CallFunc_GetNetworkDataCache_ReturnValue",
        "Flags": "RF_Public",
        "ElementSize": 8,
        "PropertyClass": {
          "ObjectName": "Class'SBNetworkDataCache'",
          "ObjectPath": "/Script/SkyBlue"
        }
      },
      {
        "Type": "ObjectProperty",
        "Name": "CallFunc_GetOwnItemList_ReturnValue",
        "Flags": "RF_Public",
        "ElementSize": 8,
        "PropertyClass": {
          "ObjectName": "Class'SBOwnItemList'",
          "ObjectPath": "/Script/SkyBlue"
        }
      },
      {
        "Type": "ObjectProperty",
        "Name": "CallFunc_GetSBPlayerController_ReturnValue",
        "Flags": "RF_Public",
        "ElementSize": 8,
        "PropertyClass": {
          "ObjectName": "Class'SBPlayerController'",
          "ObjectPath": "/Script/SkyBlue"
        }
      },
      {
        "Type": "BoolProperty",
        "Name": "CallFunc_IsValid_ReturnValue",
        "Flags": "RF_Public",
        "ElementSize": 1,
        "FieldSize": 1,
        "ByteOffset": 0,
        "ByteMask": 1,
        "FieldMask": 255,
        "BoolSize": 1,
        "bIsNativeBool": true
      },
      {
        "Type": "ObjectProperty",
        "Name": "CallFunc_GetPlayerLiquidMemoryComponent_ReturnValue",
        "Flags": "RF_Public",
        "ElementSize": 8,
        "PropertyFlags": "InstancedReference",
        "PropertyClass": {
          "ObjectName": "Class'SBPlayerLiquidMemoryComponent'",
          "ObjectPath": "/Script/SkyBlue"
        }
      },
      {
        "Type": "IntProperty",
        "Name": "K2Node_CustomEvent_InRetCode",
        "Flags": "RF_Public",
        "ElementSize": 4,
        "PropertyFlags": "ConstParm"
      },
      {
        "Type": "ArrayProperty",
        "Name": "K2Node_CustomEvent_InUpdatedLiquidMemoryInfos",
        "Flags": "RF_Public",
        "ElementSize": 16,
        "PropertyFlags": "ConstParm | ReferenceParm",
        "Inner": {
          "Type": "StructProperty",
          "Name": "K2Node_CustomEvent_InUpdatedLiquidMemoryInfos",
          "Flags": "RF_Public",
          "ElementSize": 40,
          "Struct": {
            "ObjectName": "ScriptStruct'SBLiquidMemoryInfo'",
            "ObjectPath": "/Script/SkyBlue"
          }
        }
      }
    ],
    "FunctionFlags": "FUNC_Final | FUNC_UbergraphFunction | FUNC_HasDefaults"
  },
  {
    "Type": "Function",
    "Name": "CustomEvent_0",
    "Outer": "PlayerGaugeBagCapacity_C",
    "Class": "UScriptClass'Function'",
    "ChildProperties": [
      {
        "Type": "IntProperty",
        "Name": "InRetCode",
        "Flags": "RF_Public",
        "ElementSize": 4,
        "PropertyFlags": "ConstParm | BlueprintVisible | BlueprintReadOnly | Parm"
      },
      {
        "Type": "ArrayProperty",
        "Name": "InUpdatedLiquidMemoryInfos",
        "Flags": "RF_Public",
        "ElementSize": 16,
        "PropertyFlags": "ConstParm | BlueprintVisible | BlueprintReadOnly | Parm | OutParm | ReferenceParm",
        "Inner": {
          "Type": "StructProperty",
          "Name": "InUpdatedLiquidMemoryInfos",
          "Flags": "RF_Public",
          "ElementSize": 40,
          "Struct": {
            "ObjectName": "ScriptStruct'SBLiquidMemoryInfo'",
            "ObjectPath": "/Script/SkyBlue"
          }
        }
      }
    ],
    "FunctionFlags": "FUNC_HasOutParms | FUNC_BlueprintCallable | FUNC_BlueprintEvent"
  },
  {
    "Type": "Function",
    "Name": "CustomEvent_2",
    "Outer": "PlayerGaugeBagCapacity_C",
    "Class": "UScriptClass'Function'",
    "FunctionFlags": "FUNC_BlueprintCallable | FUNC_BlueprintEvent"
  },
  {
    "Type": "Function",
    "Name": "Construct",
    "Outer": "PlayerGaugeBagCapacity_C",
    "Class": "UScriptClass'Function'",
    "SuperStruct": {
      "ObjectName": "Function'UserWidget:Construct'",
      "ObjectPath": "/Script/UMG"
    },
    "FunctionFlags": "FUNC_BlueprintCosmetic | FUNC_Event | FUNC_Public | FUNC_BlueprintEvent"
  },
  {
    "Type": "Function",
    "Name": "Update_Internal",
    "Outer": "PlayerGaugeBagCapacity_C",
    "Class": "UScriptClass'Function'",
    "ChildProperties": [
      {
        "Type": "ObjectProperty",
        "Name": "TmpInventory",
        "Flags": "RF_Public",
        "ElementSize": 8,
        "PropertyFlags": "Edit | BlueprintVisible",
        "PropertyClass": {
          "ObjectName": "Class'SBOwnItemListContainer'",
          "ObjectPath": "/Script/SkyBlue"
        }
      },
      {
        "Type": "ByteProperty",
        "Name": "CallFunc_MakeLiteralByte_ReturnValue",
        "Flags": "RF_Public",
        "ElementSize": 1,
        "Enum": null
      },
      {
        "Type": "BoolProperty",
        "Name": "Temp_bool_Variable",
        "Flags": "RF_Public",
        "ElementSize": 1,
        "FieldSize": 1,
        "ByteOffset": 0,
        "ByteMask": 1,
        "FieldMask": 255,
        "BoolSize": 1,
        "bIsNativeBool": true
      },
      {
        "Type": "TextProperty",
        "Name": "CallFunc_Conv_IntToText_ReturnValue",
        "Flags": "RF_Public",
        "ElementSize": 24
      },
      {
        "Type": "ByteProperty",
        "Name": "CallFunc_MakeLiteralByte_ReturnValue_1",
        "Flags": "RF_Public",
        "ElementSize": 1,
        "Enum": null
      },
      {
        "Type": "TextProperty",
        "Name": "CallFunc_Conv_IntToText_ReturnValue_1",
        "Flags": "RF_Public",
        "ElementSize": 24
      },
      {
        "Type": "BoolProperty",
        "Name": "Temp_bool_Variable_1",
        "Flags": "RF_Public",
        "ElementSize": 1,
        "FieldSize": 1,
        "ByteOffset": 0,
        "ByteMask": 1,
        "FieldMask": 255,
        "BoolSize": 1,
        "bIsNativeBool": true
      },
      {
        "Type": "StructProperty",
        "Name": "K2Node_MakeStruct_SlateColor",
        "Flags": "RF_Public",
        "ElementSize": 40,
        "Struct": {
          "ObjectName": "ScriptStruct'SlateColor'",
          "ObjectPath": "/Script/SlateCore"
        }
      },
      {
        "Type": "EnumProperty",
        "Name": "K2Node_Select_Default",
        "Flags": "RF_Public",
        "ElementSize": 1,
        "Enum": {
          "ObjectName": "Enum'ESlateVisibility'",
          "ObjectPath": "/Script/UMG"
        },
        "UnderlyingProp": {
          "Type": "ByteProperty",
          "Name": "UnderlyingType",
          "Flags": "RF_Public",
          "ElementSize": 1,
          "Enum": null
        }
      },
      {
        "Type": "StructProperty",
        "Name": "K2Node_MakeStruct_SlateColor_1",
        "Flags": "RF_Public",
        "ElementSize": 40,
        "Struct": {
          "ObjectName": "ScriptStruct'SlateColor'",
          "ObjectPath": "/Script/SlateCore"
        }
      },
      {
        "Type": "StructProperty",
        "Name": "K2Node_MakeStruct_SlateColor_2",
        "Flags": "RF_Public",
        "ElementSize": 40,
        "Struct": {
          "ObjectName": "ScriptStruct'SlateColor'",
          "ObjectPath": "/Script/SlateCore"
        }
      },
      {
        "Type": "BoolProperty",
        "Name": "CallFunc_GreaterEqual_IntInt_ReturnValue",
        "Flags": "RF_Public",
        "ElementSize": 1,
        "FieldSize": 1,
        "ByteOffset": 0,
        "ByteMask": 1,
        "FieldMask": 255,
        "BoolSize": 1,
        "bIsNativeBool": true
      },
      {
        "Type": "StructProperty",
        "Name": "K2Node_Select_Default_1",
        "Flags": "RF_Public",
        "ElementSize": 40,
        "Struct": {
          "ObjectName": "ScriptStruct'SlateColor'",
          "ObjectPath": "/Script/SlateCore"
        }
      },
      {
        "Type": "StructProperty",
        "Name": "K2Node_MakeStruct_SlateColor_3",
        "Flags": "RF_Public",
        "ElementSize": 40,
        "Struct": {
          "ObjectName": "ScriptStruct'SlateColor'",
          "ObjectPath": "/Script/SlateCore"
        }
      },
      {
        "Type": "ObjectProperty",
        "Name": "CallFunc_GetInventory_ReturnValue",
        "Flags": "RF_Public",
        "ElementSize": 8,
        "PropertyClass": {
          "ObjectName": "Class'SBOwnItemListContainer'",
          "ObjectPath": "/Script/SkyBlue"
        }
      },
      {
        "Type": "BoolProperty",
        "Name": "CallFunc_GetIsBoostCapacity_ReturnValue",
        "Flags": "RF_Public",
        "ElementSize": 1,
        "FieldSize": 1,
        "ByteOffset": 0,
        "ByteMask": 1,
        "FieldMask": 255,
        "BoolSize": 1,
        "bIsNativeBool": true
      },
      {
        "Type": "BoolProperty",
        "Name": "CallFunc_NotEqual_BoolBool_ReturnValue",
        "Flags": "RF_Public",
        "ElementSize": 1,
        "FieldSize": 1,
        "ByteOffset": 0,
        "ByteMask": 1,
        "FieldMask": 255,
        "BoolSize": 1,
        "bIsNativeBool": true
      },
      {
        "Type": "IntProperty",
        "Name": "CallFunc_GetUseBlockNum_ReturnValue",
        "Flags": "RF_Public",
        "ElementSize": 4
      },
      {
        "Type": "BoolProperty",
        "Name": "CallFunc_NotEqual_IntInt_ReturnValue",
        "Flags": "RF_Public",
        "ElementSize": 1,
        "FieldSize": 1,
        "ByteOffset": 0,
        "ByteMask": 1,
        "FieldMask": 255,
        "BoolSize": 1,
        "bIsNativeBool": true
      },
      {
        "Type": "ObjectProperty",
        "Name": "CallFunc_GetInventory_ReturnValue_1",
        "Flags": "RF_Public",
        "ElementSize": 8,
        "PropertyClass": {
          "ObjectName": "Class'SBOwnItemListContainer'",
          "ObjectPath": "/Script/SkyBlue"
        }
      },
      {
        "Type": "IntProperty",
        "Name": "CallFunc_GetCapacity_ReturnValue",
        "Flags": "RF_Public",
        "ElementSize": 4
      },
      {
        "Type": "BoolProperty",
        "Name": "CallFunc_NotEqual_IntInt_ReturnValue_1",
        "Flags": "RF_Public",
        "ElementSize": 1,
        "FieldSize": 1,
        "ByteOffset": 0,
        "ByteMask": 1,
        "FieldMask": 255,
        "BoolSize": 1,
        "bIsNativeBool": true
      }
    ],
    "FunctionFlags": "FUNC_Public | FUNC_HasDefaults | FUNC_BlueprintCallable | FUNC_BlueprintEvent"
  },
  {
    "Type": "WidgetBlueprintGeneratedClass",
    "Name": "PlayerGaugeBagCapacity_C",
    "Class": "UScriptClass'WidgetBlueprintGeneratedClass'",
    "Properties": {
      "WidgetTree": {
        "ObjectName": "WidgetTree'PlayerGaugeBagCapacity_C:WidgetTree'",
        "ObjectPath": "BLUEPROTOCOL/Content/Blueprints/UI/PlayerGauge/PlayerGaugeBagCapacity.28"
      },
      "UberGraphFunction": {
        "ObjectName": "Function'PlayerGaugeBagCapacity_C:ExecuteUbergraph_PlayerGaugeBagCapacity'",
        "ObjectPath": "BLUEPROTOCOL/Content/Blueprints/UI/PlayerGauge/PlayerGaugeBagCapacity.0"
      }
    },
    "SuperStruct": {
      "ObjectName": "Class'UserWidget'",
      "ObjectPath": "/Script/UMG"
    },
    "Children": [
      {
        "ObjectName": "Function'PlayerGaugeBagCapacity_C:Update_Internal'",
        "ObjectPath": "BLUEPROTOCOL/Content/Blueprints/UI/PlayerGauge/PlayerGaugeBagCapacity.4"
      },
      {
        "ObjectName": "Function'PlayerGaugeBagCapacity_C:Construct'",
        "ObjectPath": "BLUEPROTOCOL/Content/Blueprints/UI/PlayerGauge/PlayerGaugeBagCapacity.3"
      },
      {
        "ObjectName": "Function'PlayerGaugeBagCapacity_C:CustomEvent_2'",
        "ObjectPath": "BLUEPROTOCOL/Content/Blueprints/UI/PlayerGauge/PlayerGaugeBagCapacity.2"
      },
      {
        "ObjectName": "Function'PlayerGaugeBagCapacity_C:CustomEvent_0'",
        "ObjectPath": "BLUEPROTOCOL/Content/Blueprints/UI/PlayerGauge/PlayerGaugeBagCapacity.1"
      },
      {
        "ObjectName": "Function'PlayerGaugeBagCapacity_C:ExecuteUbergraph_PlayerGaugeBagCapacity'",
        "ObjectPath": "BLUEPROTOCOL/Content/Blueprints/UI/PlayerGauge/PlayerGaugeBagCapacity.0"
      }
    ],
    "ChildProperties": [
      {
        "Type": "StructProperty",
        "Name": "UberGraphFrame",
        "Flags": "RF_Public | RF_LoadCompleted",
        "ElementSize": 16,
        "PropertyFlags": "Transient | DuplicateTransient",
        "Struct": {
          "ObjectName": "ScriptStruct'PointerToUberGraphFrame'",
          "ObjectPath": "/Script/Engine"
        }
      },
      {
        "Type": "ObjectProperty",
        "Name": "LiquidGrp",
        "Flags": "RF_Public | RF_LoadCompleted",
        "ElementSize": 8,
        "PropertyFlags": "BlueprintVisible | ExportObject | InstancedReference | RepSkip | PersistentInstance",
        "PropertyClass": {
          "ObjectName": "Class'CanvasPanel'",
          "ObjectPath": "/Script/UMG"
        }
      },
      {
        "Type": "ObjectProperty",
        "Name": "Text_Capacity",
        "Flags": "RF_Public | RF_LoadCompleted",
        "ElementSize": 8,
        "PropertyFlags": "BlueprintVisible | ExportObject | InstancedReference | RepSkip | PersistentInstance",
        "PropertyClass": {
          "ObjectName": "Class'TextBlock'",
          "ObjectPath": "/Script/UMG"
        }
      },
      {
        "Type": "ObjectProperty",
        "Name": "Text_UseNum",
        "Flags": "RF_Public | RF_LoadCompleted",
        "ElementSize": 8,
        "PropertyFlags": "BlueprintVisible | ExportObject | InstancedReference | RepSkip | PersistentInstance",
        "PropertyClass": {
          "ObjectName": "Class'TextBlock'",
          "ObjectPath": "/Script/UMG"
        }
      },
      {
        "Type": "IntProperty",
        "Name": "CapacityNum",
        "Flags": "RF_Public | RF_LoadCompleted",
        "ElementSize": 4,
        "PropertyFlags": "Edit | BlueprintVisible | DisableEditOnInstance"
      },
      {
        "Type": "IntProperty",
        "Name": "UseNum",
        "Flags": "RF_Public | RF_LoadCompleted",
        "ElementSize": 4,
        "PropertyFlags": "Edit | BlueprintVisible | DisableEditOnInstance"
      },
      {
        "Type": "BoolProperty",
        "Name": "IsBoostCapacity",
        "Flags": "RF_Public | RF_LoadCompleted",
        "ElementSize": 1,
        "PropertyFlags": "Edit | BlueprintVisible | DisableEditOnInstance",
        "FieldSize": 1,
        "ByteOffset": 0,
        "ByteMask": 1,
        "FieldMask": 255,
        "BoolSize": 1,
        "bIsNativeBool": true
      }
    ],
    "FuncMap": {
      "ExecuteUbergraph_PlayerGaugeBagCapacity": {
        "ObjectName": "Function'PlayerGaugeBagCapacity_C:ExecuteUbergraph_PlayerGaugeBagCapacity'",
        "ObjectPath": "BLUEPROTOCOL/Content/Blueprints/UI/PlayerGauge/PlayerGaugeBagCapacity.0"
      },
      "CustomEvent_0": {
        "ObjectName": "Function'PlayerGaugeBagCapacity_C:CustomEvent_0'",
        "ObjectPath": "BLUEPROTOCOL/Content/Blueprints/UI/PlayerGauge/PlayerGaugeBagCapacity.1"
      },
      "CustomEvent_2": {
        "ObjectName": "Function'PlayerGaugeBagCapacity_C:CustomEvent_2'",
        "ObjectPath": "BLUEPROTOCOL/Content/Blueprints/UI/PlayerGauge/PlayerGaugeBagCapacity.2"
      },
      "Construct": {
        "ObjectName": "Function'PlayerGaugeBagCapacity_C:Construct'",
        "ObjectPath": "BLUEPROTOCOL/Content/Blueprints/UI/PlayerGauge/PlayerGaugeBagCapacity.3"
      },
      "Update_Internal": {
        "ObjectName": "Function'PlayerGaugeBagCapacity_C:Update_Internal'",
        "ObjectPath": "BLUEPROTOCOL/Content/Blueprints/UI/PlayerGauge/PlayerGaugeBagCapacity.4"
      }
    },
    "ClassFlags": "CLASS_Optional | CLASS_ReplicationDataIsSetUp | CLASS_EditInlineNew | CLASS_CompiledFromBlueprint | CLASS_DefaultToInstanced | CLASS_HasInstancedReference",
    "ClassWithin": {
      "ObjectName": "Class'Object'",
      "ObjectPath": "/Script/CoreUObject"
    },
    "ClassConfigName": "Engine",
    "bCooked": true,
    "ClassDefaultObject": {
      "ObjectName": "PlayerGaugeBagCapacity_C'Default__PlayerGaugeBagCapacity_C'",
      "ObjectPath": "BLUEPROTOCOL/Content/Blueprints/UI/PlayerGauge/PlayerGaugeBagCapacity.6"
    }
  },
  {
    "Type": "PlayerGaugeBagCapacity_C",
    "Name": "Default__PlayerGaugeBagCapacity_C",
    "Class": "WidgetBlueprintGeneratedClass'BLUEPROTOCOL/Content/Blueprints/UI/PlayerGauge/PlayerGaugeBagCapacity.PlayerGaugeBagCapacity_C'",
    "Properties": {
      "UberGraphFrame": {},
      "bHasScriptImplementedTick": false,
      "bHasScriptImplementedPaint": false
    }
  },
  {
    "Type": "CanvasPanel",
    "Name": "CanvasPanel_0",
    "Outer": "WidgetTree",
    "Class": "UScriptClass'CanvasPanel'",
    "Properties": {
      "Slots": [
        {
          "ObjectName": "CanvasPanelSlot'PlayerGaugeBagCapacity_C:WidgetTree.CanvasPanel_0.CanvasPanelSlot_1'",
          "ObjectPath": "BLUEPROTOCOL/Content/Blueprints/UI/PlayerGauge/PlayerGaugeBagCapacity.10"
        }
      ]
    }
  },
  {
    "Type": "CanvasPanel",
    "Name": "CanvasPanel_1",
    "Outer": "WidgetTree",
    "Class": "UScriptClass'CanvasPanel'",
    "Properties": {
      "Slots": [
        {
          "ObjectName": "CanvasPanelSlot'PlayerGaugeBagCapacity_C:WidgetTree.CanvasPanel_1.CanvasPanelSlot_3'",
          "ObjectPath": "BLUEPROTOCOL/Content/Blueprints/UI/PlayerGauge/PlayerGaugeBagCapacity.13"
        },
        {
          "ObjectName": "CanvasPanelSlot'PlayerGaugeBagCapacity_C:WidgetTree.CanvasPanel_1.CanvasPanelSlot_5'",
          "ObjectPath": "BLUEPROTOCOL/Content/Blueprints/UI/PlayerGauge/PlayerGaugeBagCapacity.14"
        },
        {
          "ObjectName": "CanvasPanelSlot'PlayerGaugeBagCapacity_C:WidgetTree.CanvasPanel_1.CanvasPanelSlot_1'",
          "ObjectPath": "BLUEPROTOCOL/Content/Blueprints/UI/PlayerGauge/PlayerGaugeBagCapacity.11"
        },
        {
          "ObjectName": "CanvasPanelSlot'PlayerGaugeBagCapacity_C:WidgetTree.CanvasPanel_1.CanvasPanelSlot_2'",
          "ObjectPath": "BLUEPROTOCOL/Content/Blueprints/UI/PlayerGauge/PlayerGaugeBagCapacity.12"
        }
      ],
      "Slot": {
        "ObjectName": "CanvasPanelSlot'PlayerGaugeBagCapacity_C:WidgetTree.CanvasPanel_0.CanvasPanelSlot_1'",
        "ObjectPath": "BLUEPROTOCOL/Content/Blueprints/UI/PlayerGauge/PlayerGaugeBagCapacity.10"
      }
    }
  },
  {
    "Type": "CanvasPanel",
    "Name": "LiquidGrp",
    "Outer": "WidgetTree",
    "Class": "UScriptClass'CanvasPanel'",
    "Properties": {
      "Slots": [
        {
          "ObjectName": "CanvasPanelSlot'PlayerGaugeBagCapacity_C:WidgetTree.LiquidGrp.CanvasPanelSlot_0'",
          "ObjectPath": "BLUEPROTOCOL/Content/Blueprints/UI/PlayerGauge/PlayerGaugeBagCapacity.15"
        }
      ],
      "Slot": {
        "ObjectName": "CanvasPanelSlot'PlayerGaugeBagCapacity_C:WidgetTree.CanvasPanel_1.CanvasPanelSlot_3'",
        "ObjectPath": "BLUEPROTOCOL/Content/Blueprints/UI/PlayerGauge/PlayerGaugeBagCapacity.13"
      },
      "bIsVariable": true
    }
  },
  {
    "Type": "CanvasPanelSlot",
    "Name": "CanvasPanelSlot_1",
    "Outer": "CanvasPanel_0",
    "Class": "UScriptClass'CanvasPanelSlot'",
    "Properties": {
      "LayoutData": {
        "Offsets": {
          "Right": 131.42857
        }
      },
      "bAutoSize": true,
      "Parent": {
        "ObjectName": "CanvasPanel'PlayerGaugeBagCapacity_C:WidgetTree.CanvasPanel_0'",
        "ObjectPath": "BLUEPROTOCOL/Content/Blueprints/UI/PlayerGauge/PlayerGaugeBagCapacity.7"
      },
      "Content": {
        "ObjectName": "CanvasPanel'PlayerGaugeBagCapacity_C:WidgetTree.CanvasPanel_1'",
        "ObjectPath": "BLUEPROTOCOL/Content/Blueprints/UI/PlayerGauge/PlayerGaugeBagCapacity.8"
      }
    }
  },
  {
    "Type": "CanvasPanelSlot",
    "Name": "CanvasPanelSlot_1",
    "Outer": "CanvasPanel_1",
    "Class": "UScriptClass'CanvasPanelSlot'",
    "Properties": {
      "LayoutData": {
        "Offsets": {
          "Right": 25.0,
          "Bottom": 25.0
        }
      },
      "Parent": {
        "ObjectName": "CanvasPanel'PlayerGaugeBagCapacity_C:WidgetTree.CanvasPanel_1'",
        "ObjectPath": "BLUEPROTOCOL/Content/Blueprints/UI/PlayerGauge/PlayerGaugeBagCapacity.8"
      },
      "Content": {
        "ObjectName": "Image'PlayerGaugeBagCapacity_C:WidgetTree.Icon_Bag'",
        "ObjectPath": "BLUEPROTOCOL/Content/Blueprints/UI/PlayerGauge/PlayerGaugeBagCapacity.20"
      }
    }
  },
  {
    "Type": "CanvasPanelSlot",
    "Name": "CanvasPanelSlot_2",
    "Outer": "CanvasPanel_1",
    "Class": "UScriptClass'CanvasPanelSlot'",
    "Properties": {
      "LayoutData": {
        "Offsets": {
          "Left": 29.0,
          "Top": 3.0,
          "Right": 68.0,
          "Bottom": 22.0
        }
      },
      "Parent": {
        "ObjectName": "CanvasPanel'PlayerGaugeBagCapacity_C:WidgetTree.CanvasPanel_1'",
        "ObjectPath": "BLUEPROTOCOL/Content/Blueprints/UI/PlayerGauge/PlayerGaugeBagCapacity.8"
      },
      "Content": {
        "ObjectName": "ScaleBox'PlayerGaugeBagCapacity_C:WidgetTree.ScaleBox_0'",
        "ObjectPath": "BLUEPROTOCOL/Content/Blueprints/UI/PlayerGauge/PlayerGaugeBagCapacity.23"
      }
    }
  },
  {
    "Type": "CanvasPanelSlot",
    "Name": "CanvasPanelSlot_3",
    "Outer": "CanvasPanel_1",
    "Class": "UScriptClass'CanvasPanelSlot'",
    "Properties": {
      "LayoutData": {
        "Offsets": {
          "Right": 120.0,
          "Bottom": 36.0
        }
      },
      "Parent": {
        "ObjectName": "CanvasPanel'PlayerGaugeBagCapacity_C:WidgetTree.CanvasPanel_1'",
        "ObjectPath": "BLUEPROTOCOL/Content/Blueprints/UI/PlayerGauge/PlayerGaugeBagCapacity.8"
      },
      "Content": {
        "ObjectName": "CanvasPanel'PlayerGaugeBagCapacity_C:WidgetTree.LiquidGrp'",
        "ObjectPath": "BLUEPROTOCOL/Content/Blueprints/UI/PlayerGauge/PlayerGaugeBagCapacity.9"
      }
    }
  },
  {
    "Type": "CanvasPanelSlot",
    "Name": "CanvasPanelSlot_5",
    "Outer": "CanvasPanel_1",
    "Class": "UScriptClass'CanvasPanelSlot'",
    "Properties": {
      "LayoutData": {
        "Offsets": {
          "Left": 1.0,
          "Top": 1.0,
          "Right": 25.0,
          "Bottom": 25.0
        }
      },
      "Parent": {
        "ObjectName": "CanvasPanel'PlayerGaugeBagCapacity_C:WidgetTree.CanvasPanel_1'",
        "ObjectPath": "BLUEPROTOCOL/Content/Blueprints/UI/PlayerGauge/PlayerGaugeBagCapacity.8"
      },
      "Content": {
        "ObjectName": "Image'PlayerGaugeBagCapacity_C:WidgetTree.Icon_BagShadow'",
        "ObjectPath": "BLUEPROTOCOL/Content/Blueprints/UI/PlayerGauge/PlayerGaugeBagCapacity.21"
      }
    }
  },
  {
    "Type": "CanvasPanelSlot",
    "Name": "CanvasPanelSlot_0",
    "Outer": "LiquidGrp",
    "Class": "UScriptClass'CanvasPanelSlot'",
    "Properties": {
      "LayoutData": {
        "Offsets": {
          "Left": 45.0,
          "Top": 21.0,
          "Right": 80.0,
          "Bottom": 6.0
        }
      },
      "Parent": {
        "ObjectName": "CanvasPanel'PlayerGaugeBagCapacity_C:WidgetTree.LiquidGrp'",
        "ObjectPath": "BLUEPROTOCOL/Content/Blueprints/UI/PlayerGauge/PlayerGaugeBagCapacity.9"
      },
      "Content": {
        "ObjectName": "Image'PlayerGaugeBagCapacity_C:WidgetTree.Image_656'",
        "ObjectPath": "BLUEPROTOCOL/Content/Blueprints/UI/PlayerGauge/PlayerGaugeBagCapacity.22"
      }
    }
  },
  {
    "Type": "HorizontalBox",
    "Name": "HorizontalBox_0",
    "Outer": "WidgetTree",
    "Class": "UScriptClass'HorizontalBox'",
    "Properties": {
      "Slots": [
        {
          "ObjectName": "HorizontalBoxSlot'PlayerGaugeBagCapacity_C:WidgetTree.HorizontalBox_0.HorizontalBoxSlot_0'",
          "ObjectPath": "BLUEPROTOCOL/Content/Blueprints/UI/PlayerGauge/PlayerGaugeBagCapacity.17"
        },
        {
          "ObjectName": "HorizontalBoxSlot'PlayerGaugeBagCapacity_C:WidgetTree.HorizontalBox_0.HorizontalBoxSlot_1'",
          "ObjectPath": "BLUEPROTOCOL/Content/Blueprints/UI/PlayerGauge/PlayerGaugeBagCapacity.18"
        },
        {
          "ObjectName": "HorizontalBoxSlot'PlayerGaugeBagCapacity_C:WidgetTree.HorizontalBox_0.HorizontalBoxSlot_2'",
          "ObjectPath": "BLUEPROTOCOL/Content/Blueprints/UI/PlayerGauge/PlayerGaugeBagCapacity.19"
        }
      ],
      "Slot": {
        "ObjectName": "ScaleBoxSlot'PlayerGaugeBagCapacity_C:WidgetTree.ScaleBox_0.ScaleBoxSlot_0'",
        "ObjectPath": "BLUEPROTOCOL/Content/Blueprints/UI/PlayerGauge/PlayerGaugeBagCapacity.24"
      }
    }
  },
  {
    "Type": "HorizontalBoxSlot",
    "Name": "HorizontalBoxSlot_0",
    "Outer": "HorizontalBox_0",
    "Class": "UScriptClass'HorizontalBoxSlot'",
    "Properties": {
      "VerticalAlignment": "VAlign_Center",
      "Parent": {
        "ObjectName": "HorizontalBox'PlayerGaugeBagCapacity_C:WidgetTree.HorizontalBox_0'",
        "ObjectPath": "BLUEPROTOCOL/Content/Blueprints/UI/PlayerGauge/PlayerGaugeBagCapacity.16"
      },
      "Content": {
        "ObjectName": "TextBlock'PlayerGaugeBagCapacity_C:WidgetTree.Text_UseNum'",
        "ObjectPath": "BLUEPROTOCOL/Content/Blueprints/UI/PlayerGauge/PlayerGaugeBagCapacity.27"
      }
    }
  },
  {
    "Type": "HorizontalBoxSlot",
    "Name": "HorizontalBoxSlot_1",
    "Outer": "HorizontalBox_0",
    "Class": "UScriptClass'HorizontalBoxSlot'",
    "Properties": {
      "HorizontalAlignment": "HAlign_Left",
      "VerticalAlignment": "VAlign_Center",
      "Parent": {
        "ObjectName": "HorizontalBox'PlayerGaugeBagCapacity_C:WidgetTree.HorizontalBox_0'",
        "ObjectPath": "BLUEPROTOCOL/Content/Blueprints/UI/PlayerGauge/PlayerGaugeBagCapacity.16"
      },
      "Content": {
        "ObjectName": "TextBlock'PlayerGaugeBagCapacity_C:WidgetTree.Text_Slash'",
        "ObjectPath": "BLUEPROTOCOL/Content/Blueprints/UI/PlayerGauge/PlayerGaugeBagCapacity.26"
      }
    }
  },
  {
    "Type": "HorizontalBoxSlot",
    "Name": "HorizontalBoxSlot_2",
    "Outer": "HorizontalBox_0",
    "Class": "UScriptClass'HorizontalBoxSlot'",
    "Properties": {
      "HorizontalAlignment": "HAlign_Right",
      "VerticalAlignment": "VAlign_Center",
      "Parent": {
        "ObjectName": "HorizontalBox'PlayerGaugeBagCapacity_C:WidgetTree.HorizontalBox_0'",
        "ObjectPath": "BLUEPROTOCOL/Content/Blueprints/UI/PlayerGauge/PlayerGaugeBagCapacity.16"
      },
      "Content": {
        "ObjectName": "TextBlock'PlayerGaugeBagCapacity_C:WidgetTree.Text_Capacity'",
        "ObjectPath": "BLUEPROTOCOL/Content/Blueprints/UI/PlayerGauge/PlayerGaugeBagCapacity.25"
      }
    }
  },
  {
    "Type": "Image",
    "Name": "Icon_Bag",
    "Outer": "WidgetTree",
    "Class": "UScriptClass'Image'",
    "Properties": {
      "Brush": {
        "ImageSize": {
          "X": 30.0,
          "Y": 30.0
        },
        "ResourceObject": {
          "ObjectName": "Texture2D'UI_CmnIconStorage_S_Bag'",
          "ObjectPath": "BLUEPROTOCOL/Content/UI/Common/UI_CmnIconStorage_S_Bag.0"
        }
      },
      "Slot": {
        "ObjectName": "CanvasPanelSlot'PlayerGaugeBagCapacity_C:WidgetTree.CanvasPanel_1.CanvasPanelSlot_1'",
        "ObjectPath": "BLUEPROTOCOL/Content/Blueprints/UI/PlayerGauge/PlayerGaugeBagCapacity.11"
      },
      "bIsVariable": false
    }
  },
  {
    "Type": "Image",
    "Name": "Icon_BagShadow",
    "Outer": "WidgetTree",
    "Class": "UScriptClass'Image'",
    "Properties": {
      "Brush": {
        "ImageSize": {
          "X": 30.0,
          "Y": 30.0
        },
        "ResourceObject": {
          "ObjectName": "Texture2D'UI_CmnIconStorage_S_Bag'",
          "ObjectPath": "BLUEPROTOCOL/Content/UI/Common/UI_CmnIconStorage_S_Bag.0"
        }
      },
      "ColorAndOpacity": {
        "R": 0.0,
        "G": 0.0,
        "B": 0.0,
        "A": 0.6,
        "Hex": "99000000"
      },
      "Slot": {
        "ObjectName": "CanvasPanelSlot'PlayerGaugeBagCapacity_C:WidgetTree.CanvasPanel_1.CanvasPanelSlot_5'",
        "ObjectPath": "BLUEPROTOCOL/Content/Blueprints/UI/PlayerGauge/PlayerGaugeBagCapacity.14"
      },
      "bIsVariable": false
    }
  },
  {
    "Type": "Image",
    "Name": "Image_656",
    "Outer": "WidgetTree",
    "Class": "UScriptClass'Image'",
    "Properties": {
      "Brush": {
        "ResourceObject": {
          "ObjectName": "MaterialInstanceConstant'MI_UI_PlayerGaugeBg02'",
          "ObjectPath": "BLUEPROTOCOL/Content/UI/PlayerGauge/MI_UI_PlayerGaugeBg02.0"
        }
      },
      "Slot": {
        "ObjectName": "CanvasPanelSlot'PlayerGaugeBagCapacity_C:WidgetTree.LiquidGrp.CanvasPanelSlot_0'",
        "ObjectPath": "BLUEPROTOCOL/Content/Blueprints/UI/PlayerGauge/PlayerGaugeBagCapacity.15"
      },
      "bIsVariable": false
    }
  },
  {
    "Type": "ScaleBox",
    "Name": "ScaleBox_0",
    "Outer": "WidgetTree",
    "Class": "UScriptClass'ScaleBox'",
    "Properties": {
      "Stretch": "EStretch::ScaleToFitX",
      "StretchDirection": "EStretchDirection::DownOnly",
      "Slots": [
        {
          "ObjectName": "ScaleBoxSlot'PlayerGaugeBagCapacity_C:WidgetTree.ScaleBox_0.ScaleBoxSlot_0'",
          "ObjectPath": "BLUEPROTOCOL/Content/Blueprints/UI/PlayerGauge/PlayerGaugeBagCapacity.24"
        }
      ],
      "Slot": {
        "ObjectName": "CanvasPanelSlot'PlayerGaugeBagCapacity_C:WidgetTree.CanvasPanel_1.CanvasPanelSlot_2'",
        "ObjectPath": "BLUEPROTOCOL/Content/Blueprints/UI/PlayerGauge/PlayerGaugeBagCapacity.12"
      }
    }
  },
  {
    "Type": "ScaleBoxSlot",
    "Name": "ScaleBoxSlot_0",
    "Outer": "ScaleBox_0",
    "Class": "UScriptClass'ScaleBoxSlot'",
    "Properties": {
      "HorizontalAlignment": "HAlign_Right",
      "Parent": {
        "ObjectName": "ScaleBox'PlayerGaugeBagCapacity_C:WidgetTree.ScaleBox_0'",
        "ObjectPath": "BLUEPROTOCOL/Content/Blueprints/UI/PlayerGauge/PlayerGaugeBagCapacity.23"
      },
      "Content": {
        "ObjectName": "HorizontalBox'PlayerGaugeBagCapacity_C:WidgetTree.HorizontalBox_0'",
        "ObjectPath": "BLUEPROTOCOL/Content/Blueprints/UI/PlayerGauge/PlayerGaugeBagCapacity.16"
      }
    }
  },
  {
    "Type": "TextBlock",
    "Name": "Text_Capacity",
    "Outer": "WidgetTree",
    "Class": "UScriptClass'TextBlock'",
    "Properties": {
      "Text": {
        "Namespace": "",
        "Key": "B93FEADF4894C249ACB72DB9854AC1B7",
        "SourceString": "000",
        "LocalizedString": "000"
      },
      "Font": {
        "FontObject": {
          "ObjectName": "Font'CenturyGothicPro-Bold'",
          "ObjectPath": "BLUEPROTOCOL/Content/UI/Font/CenturyGothicPro-Bold.0"
        },
        "TypefaceFontName": "Default",
        "Size": 12
      },
      "ShadowColorAndOpacity": {
        "R": 0.0,
        "G": 0.0,
        "B": 0.0,
        "A": 0.6,
        "Hex": "99000000"
      },
      "Slot": {
        "ObjectName": "HorizontalBoxSlot'PlayerGaugeBagCapacity_C:WidgetTree.HorizontalBox_0.HorizontalBoxSlot_2'",
        "ObjectPath": "BLUEPROTOCOL/Content/Blueprints/UI/PlayerGauge/PlayerGaugeBagCapacity.19"
      },
      "bIsVariable": true
    }
  },
  {
    "Type": "TextBlock",
    "Name": "Text_Slash",
    "Outer": "WidgetTree",
    "Class": "UScriptClass'TextBlock'",
    "Properties": {
      "Text": {
        "Namespace": "",
        "Key": "355A5E164DB0A63CE74B6DB6BBF47531",
        "SourceString": "/",
        "LocalizedString": "/"
      },
      "Font": {
        "FontObject": {
          "ObjectName": "Font'CenturyGothicPro-Bold'",
          "ObjectPath": "BLUEPROTOCOL/Content/UI/Font/CenturyGothicPro-Bold.0"
        },
        "TypefaceFontName": "Default",
        "Size": 12
      },
      "ShadowColorAndOpacity": {
        "R": 0.0,
        "G": 0.0,
        "B": 0.0,
        "A": 0.6,
        "Hex": "99000000"
      },
      "Slot": {
        "ObjectName": "HorizontalBoxSlot'PlayerGaugeBagCapacity_C:WidgetTree.HorizontalBox_0.HorizontalBoxSlot_1'",
        "ObjectPath": "BLUEPROTOCOL/Content/Blueprints/UI/PlayerGauge/PlayerGaugeBagCapacity.18"
      }
    }
  },
  {
    "Type": "TextBlock",
    "Name": "Text_UseNum",
    "Outer": "WidgetTree",
    "Class": "UScriptClass'TextBlock'",
    "Properties": {
      "Text": {
        "Namespace": "",
        "Key": "3DC5ABBF4AB135024AC2EE94C3A46264",
        "SourceString": "0",
        "LocalizedString": "0"
      },
      "Font": {
        "FontObject": {
          "ObjectName": "Font'CenturyGothicPro-Bold'",
          "ObjectPath": "BLUEPROTOCOL/Content/UI/Font/CenturyGothicPro-Bold.0"
        },
        "TypefaceFontName": "Default",
        "Size": 12
      },
      "ShadowColorAndOpacity": {
        "R": 0.0,
        "G": 0.0,
        "B": 0.0,
        "A": 0.6,
        "Hex": "99000000"
      },
      "Justification": "ETextJustify::Right",
      "Slot": {
        "ObjectName": "HorizontalBoxSlot'PlayerGaugeBagCapacity_C:WidgetTree.HorizontalBox_0.HorizontalBoxSlot_0'",
        "ObjectPath": "BLUEPROTOCOL/Content/Blueprints/UI/PlayerGauge/PlayerGaugeBagCapacity.17"
      },
      "bIsVariable": true
    }
  },
  {
    "Type": "WidgetTree",
    "Name": "WidgetTree",
    "Outer": "PlayerGaugeBagCapacity_C",
    "Class": "UScriptClass'WidgetTree'",
    "Properties": {
      "RootWidget": {
        "ObjectName": "CanvasPanel'PlayerGaugeBagCapacity_C:WidgetTree.CanvasPanel_0'",
        "ObjectPath": "BLUEPROTOCOL/Content/Blueprints/UI/PlayerGauge/PlayerGaugeBagCapacity.7"
      }
    }
  }
]