[
  {
    "Type": "CharaPartsColorList",
    "Name": "CL_CH_mob_F400_nbl_bdu_001",
    "Class": "UScriptClass'CharaPartsColorList'",
    "Properties": {
      "ColorList": [
        {
          "IsValid": true,
          "Name": "Default",
          "BaseColor1": {
            "R": 1.0,
            "G": 1.0,
            "B": 1.0,
            "A": 1.0,
            "Hex": "FFFFFF"
          },
          "BaseColor2": {
            "R": 1.0,
            "G": 1.0,
            "B": 1.0,
            "A": 1.0,
            "Hex": "FFFFFF"
          },
          "BaseColor3": {
            "R": 1.0,
            "G": 1.0,
            "B": 1.0,
            "A": 1.0,
            "Hex": "FFFFFF"
          },
          "BaseColor4": {
            "R": 1.0,
            "G": 1.0,
            "B": 1.0,
            "A": 1.0,
            "Hex": "FFFFFF"
          }
        },
        {
          "IsValid": true,
          "Name": "Color1",
          "BaseColor1": {
            "R": 0.214,
            "G": 0.3,
            "B": 0.18,
            "A": 1.0,
            "Hex": "7F9576"
          },
          "BaseColor2": {
            "R": 0.8,
            "G": 0.784,
            "B": 0.64,
            "A": 1.0,
            "Hex": "E8E5D2"
          },
          "BaseColor3": {
            "R": 0.688077,
            "G": 0.7,
            "B": 0.3423,
            "A": 1.0,
            "Hex": "D9DA9E"
          },
          "BaseColor4": {
            "R": 0.222917,
            "G": 0.557292,
            "B": 0.334375,
            "A": 1.0,
            "Hex": "82C59D"
          }
        },
        {
          "IsValid": true,
          "Name": "Color2",
          "BaseColor1": {
            "R": 0.105,
            "G": 0.2155,
            "B": 0.3,
            "A": 1.0,
            "Hex": "5B8095"
          },
          "BaseColor2": {
            "R": 0.8,
            "G": 0.64,
            "B": 0.642667,
            "A": 1.0,
            "Hex": "E8D2D2"
          },
          "BaseColor3": {
            "R": 0.56,
            "G": 0.7,
            "B": 0.618333,
            "A": 1.0,
            "Hex": "C6DACE"
          },
          "BaseColor4": {
            "R": 0.8,
            "G": 0.435428,
            "B": 0.16,
            "A": 1.0,
            "Hex": "E8B06F"
          }
        },
        {
          "IsValid": true,
          "Name": "Color3",
          "BaseColor1": {
            "R": 0.8,
            "G": 0.706667,
            "B": 0.64,
            "A": 1.0,
            "Hex": "E8DBD2"
          },
          "BaseColor2": {
            "R": 0.8,
            "G": 0.784,
            "B": 0.64,
            "A": 1.0,
            "Hex": "E8E5D2"
          },
          "BaseColor3": {
            "R": 0.541333,
            "G": 0.7,
            "B": 0.42,
            "A": 1.0,
            "Hex": "C3DAAE"
          },
          "BaseColor4": {
            "R": 0.455,
            "G": 0.64025,
            "B": 0.65,
            "A": 1.0,
            "Hex": "B4D2D3"
          }
        },
        {
          "IsValid": true,
          "Name": "Color4",
          "BaseColor1": {
            "R": 0.4,
            "G": 0.16,
            "B": 0.196,
            "A": 1.0,
            "Hex": "AA6F7A"
          },
          "BaseColor2": {
            "R": 0.2,
            "G": 0.12,
            "B": 0.12,
            "A": 1.0,
            "Hex": "7C6161"
          },
          "BaseColor3": {
            "R": 0.8,
            "G": 0.7196,
            "B": 0.532,
            "A": 1.0,
            "Hex": "E8DDC1"
          },
          "BaseColor4": {
            "R": 0.411458,
            "G": 0.288021,
            "B": 0.368255,
            "A": 1.0,
            "Hex": "AC92A4"
          }
        },
        {
          "IsValid": false,
          "Name": "Color5",
          "BaseColor1": {
            "R": 1.0,
            "G": 1.0,
            "B": 1.0,
            "A": 1.0,
            "Hex": "FFFFFF"
          },
          "BaseColor2": {
            "R": 1.0,
            "G": 1.0,
            "B": 1.0,
            "A": 1.0,
            "Hex": "FFFFFF"
          },
          "BaseColor3": {
            "R": 1.0,
            "G": 1.0,
            "B": 1.0,
            "A": 1.0,
            "Hex": "FFFFFF"
          },
          "BaseColor4": {
            "R": 1.0,
            "G": 1.0,
            "B": 1.0,
            "A": 1.0,
            "Hex": "FFFFFF"
          }
        },
        {
          "IsValid": false,
          "Name": "Color6",
          "BaseColor1": {
            "R": 1.0,
            "G": 1.0,
            "B": 1.0,
            "A": 1.0,
            "Hex": "FFFFFF"
          },
          "BaseColor2": {
            "R": 1.0,
            "G": 1.0,
            "B": 1.0,
            "A": 1.0,
            "Hex": "FFFFFF"
          },
          "BaseColor3": {
            "R": 1.0,
            "G": 1.0,
            "B": 1.0,
            "A": 1.0,
            "Hex": "FFFFFF"
          },
          "BaseColor4": {
            "R": 1.0,
            "G": 1.0,
            "B": 1.0,
            "A": 1.0,
            "Hex": "FFFFFF"
          }
        },
        {
          "IsValid": false,
          "Name": "Color7",
          "BaseColor1": {
            "R": 1.0,
            "G": 1.0,
            "B": 1.0,
            "A": 1.0,
            "Hex": "FFFFFF"
          },
          "BaseColor2": {
            "R": 1.0,
            "G": 1.0,
            "B": 1.0,
            "A": 1.0,
            "Hex": "FFFFFF"
          },
          "BaseColor3": {
            "R": 1.0,
            "G": 1.0,
            "B": 1.0,
            "A": 1.0,
            "Hex": "FFFFFF"
          },
          "BaseColor4": {
            "R": 1.0,
            "G": 1.0,
            "B": 1.0,
            "A": 1.0,
            "Hex": "FFFFFF"
          }
        },
        {
          "IsValid": false,
          "Name": "Color8",
          "BaseColor1": {
            "R": 1.0,
            "G": 1.0,
            "B": 1.0,
            "A": 1.0,
            "Hex": "FFFFFF"
          },
          "BaseColor2": {
            "R": 1.0,
            "G": 1.0,
            "B": 1.0,
            "A": 1.0,
            "Hex": "FFFFFF"
          },
          "BaseColor3": {
            "R": 1.0,
            "G": 1.0,
            "B": 1.0,
            "A": 1.0,
            "Hex": "FFFFFF"
          },
          "BaseColor4": {
            "R": 1.0,
            "G": 1.0,
            "B": 1.0,
            "A": 1.0,
            "Hex": "FFFFFF"
          }
        },
        {
          "IsValid": false,
          "Name": "Color9",
          "BaseColor1": {
            "R": 1.0,
            "G": 1.0,
            "B": 1.0,
            "A": 1.0,
            "Hex": "FFFFFF"
          },
          "BaseColor2": {
            "R": 1.0,
            "G": 1.0,
            "B": 1.0,
            "A": 1.0,
            "Hex": "FFFFFF"
          },
          "BaseColor3": {
            "R": 1.0,
            "G": 1.0,
            "B": 1.0,
            "A": 1.0,
            "Hex": "FFFFFF"
          },
          "BaseColor4": {
            "R": 1.0,
            "G": 1.0,
            "B": 1.0,
            "A": 1.0,
            "Hex": "FFFFFF"
          }
        },
        {
          "IsValid": false,
          "Name": "Color10",
          "BaseColor1": {
            "R": 1.0,
            "G": 1.0,
            "B": 1.0,
            "A": 1.0,
            "Hex": "FFFFFF"
          },
          "BaseColor2": {
            "R": 1.0,
            "G": 1.0,
            "B": 1.0,
            "A": 1.0,
            "Hex": "FFFFFF"
          },
          "BaseColor3": {
            "R": 1.0,
            "G": 1.0,
            "B": 1.0,
            "A": 1.0,
            "Hex": "FFFFFF"
          },
          "BaseColor4": {
            "R": 1.0,
            "G": 1.0,
            "B": 1.0,
            "A": 1.0,
            "Hex": "FFFFFF"
          }
        },
        {
          "IsValid": false,
          "Name": "Color11",
          "BaseColor1": {
            "R": 1.0,
            "G": 1.0,
            "B": 1.0,
            "A": 1.0,
            "Hex": "FFFFFF"
          },
          "BaseColor2": {
            "R": 1.0,
            "G": 1.0,
            "B": 1.0,
            "A": 1.0,
            "Hex": "FFFFFF"
          },
          "BaseColor3": {
            "R": 1.0,
            "G": 1.0,
            "B": 1.0,
            "A": 1.0,
            "Hex": "FFFFFF"
          },
          "BaseColor4": {
            "R": 1.0,
            "G": 1.0,
            "B": 1.0,
            "A": 1.0,
            "Hex": "FFFFFF"
          }
        },
        {
          "IsValid": false,
          "Name": "Color12",
          "BaseColor1": {
            "R": 1.0,
            "G": 1.0,
            "B": 1.0,
            "A": 1.0,
            "Hex": "FFFFFF"
          },
          "BaseColor2": {
            "R": 1.0,
            "G": 1.0,
            "B": 1.0,
            "A": 1.0,
            "Hex": "FFFFFF"
          },
          "BaseColor3": {
            "R": 1.0,
            "G": 1.0,
            "B": 1.0,
            "A": 1.0,
            "Hex": "FFFFFF"
          },
          "BaseColor4": {
            "R": 1.0,
            "G": 1.0,
            "B": 1.0,
            "A": 1.0,
            "Hex": "FFFFFF"
          }
        },
        {
          "IsValid": false,
          "Name": "",
          "BaseColor1": {
            "R": 1.0,
            "G": 1.0,
            "B": 1.0,
            "A": 1.0,
            "Hex": "FFFFFF"
          },
          "BaseColor2": {
            "R": 1.0,
            "G": 1.0,
            "B": 1.0,
            "A": 1.0,
            "Hex": "FFFFFF"
          },
          "BaseColor3": {
            "R": 1.0,
            "G": 1.0,
            "B": 1.0,
            "A": 1.0,
            "Hex": "FFFFFF"
          },
          "BaseColor4": {
            "R": 1.0,
            "G": 1.0,
            "B": 1.0,
            "A": 1.0,
            "Hex": "FFFFFF"
          }
        }
      ]
    }
  }
]